apt_local/__init__.py
apt_local/pacman.py
apt_local/system.py
apt_local-0.0.2b1.dist-info/LICENSE
apt_local-0.0.2b1.dist-info/METADATA
apt_local-0.0.2b1.dist-info/WHEEL
apt_local-0.0.2b1.dist-info/entry_points.txt
apt_local-0.0.2b1.dist-info/top_level.txt
apt_local-0.0.2b1.dist-info/RECORD
