Metadata-Version: 2.1
Name: apt-local
Version: 0.0.2b1
Summary: Simple symlink-based package manager for local installations (without sudo)
Home-page: https://github.com/ashwinvis/apt_local
Author: Ashwin Vishnu Mohanan
Author-email: ashwinvis@protonmail.com
License: GNU General Public License v3
Keywords: apt_local
Platform: UNKNOWN
Classifier: Development Status :: 4 - Beta
Classifier: Intended Audience :: Developers
Classifier: Intended Audience :: End Users/Desktop
Classifier: Intended Audience :: System Administrators
Classifier: Intended Audience :: Science/Research
Classifier: Topic :: System :: Systems Administration
Classifier: Topic :: System :: Installation/Setup
Classifier: Topic :: Utilities
Classifier: License :: OSI Approved :: GNU General Public License v3 (GPLv3)
Classifier: Natural Language :: English
Classifier: Programming Language :: Python :: 3
Classifier: Programming Language :: Python :: 3.6
Classifier: Programming Language :: Python :: 3.7
Classifier: Programming Language :: Python :: 3.8
Requires-Python: >= 3.6
Provides-Extra: dev
Requires-Dist: sphinx (==2.0.1) ; extra == 'dev'
Requires-Dist: recommonmark (>=0.5.0) ; extra == 'dev'
Requires-Dist: sphinx-rtd-theme (==0.4.3) ; extra == 'dev'
Requires-Dist: numpydoc ; extra == 'dev'
Requires-Dist: bumpversion (==0.5.3) ; extra == 'dev'
Requires-Dist: watchdog (==0.9.0) ; extra == 'dev'
Requires-Dist: flake8 (==3.5.0) ; extra == 'dev'
Requires-Dist: tox (==3.5.2) ; extra == 'dev'
Requires-Dist: coverage (==4.5.1) ; extra == 'dev'
Requires-Dist: twine (==1.12.1) ; extra == 'dev'
Requires-Dist: readme-renderer[md] (==24.0) ; extra == 'dev'
Provides-Extra: docs
Requires-Dist: sphinx (==2.0.1) ; extra == 'docs'
Requires-Dist: recommonmark (>=0.5.0) ; extra == 'docs'
Requires-Dist: sphinx-rtd-theme (==0.4.3) ; extra == 'docs'
Requires-Dist: numpydoc ; extra == 'docs'
